antlr_v4_linter/__init__.py
antlr_v4_linter/cli/__init__.py
antlr_v4_linter/cli/main.py
antlr_v4_linter/core/config.py
antlr_v4_linter/core/linter.py
antlr_v4_linter/core/models.py
antlr_v4_linter/core/parser.py
antlr_v4_linter/core/reporter.py
antlr_v4_linter/core/rule_engine.py
antlr_v4_linter/grammars/ANTLRv4Lexer.py
antlr_v4_linter/grammars/ANTLRv4Parser.py
antlr_v4_linter/grammars/ANTLRv4ParserVisitor.py
antlr_v4_linter/grammars/LexerAdaptor.py
antlr_v4_linter/grammars/__init__.py
antlr_v4_linter/rules/__init__.py
antlr_v4_linter/rules/complexity_rules.py
antlr_v4_linter/rules/documentation_rules.py
antlr_v4_linter/rules/error_handling_rules.py
antlr_v4_linter/rules/labeling_rules.py
antlr_v4_linter/rules/naming_rules.py
antlr_v4_linter/rules/performance_rules.py
antlr_v4_linter/rules/syntax_rules.py
antlr_v4_linter/rules/token_rules.py
antlr_v4_linter-0.1.4.dist-info/licenses/LICENSE
antlr_v4_linter-0.1.4.dist-info/METADATA
antlr_v4_linter-0.1.4.dist-info/WHEEL
antlr_v4_linter-0.1.4.dist-info/entry_points.txt
antlr_v4_linter-0.1.4.dist-info/top_level.txt
antlr_v4_linter-0.1.4.dist-info/RECORD
