Metadata-Version: 2.4
Name: antlr-v4-linter
Version: 0.1.4
Summary: A comprehensive static analysis linter for ANTLR v4 grammar files
Author-email: Bytebase <support@bytebase.com>
Maintainer-email: Bytebase Team <support@bytebase.com>
License: MIT
Project-URL: Homepage, https://github.com/bytebase/antlr-v4-linter
Project-URL: Documentation, https://github.com/bytebase/antlr-v4-linter#readme
Project-URL: Repository, https://github.com/bytebase/antlr-v4-linter
Project-URL: Issues, https://github.com/bytebase/antlr-v4-linter/issues
Project-URL: Changelog, https://github.com/bytebase/antlr-v4-linter/releases
Keywords: antlr,antlr4,linter,grammar,parser,lexer,static-analysis
Classifier: Development Status :: 4 - Beta
Classifier: Intended Audience :: Developers
Classifier: License :: OSI Approved :: MIT License
Classifier: Programming Language :: Python :: 3
Classifier: Programming Language :: Python :: 3.8
Classifier: Programming Language :: Python :: 3.9
Classifier: Programming Language :: Python :: 3.10
Classifier: Programming Language :: Python :: 3.11
Classifier: Programming Language :: Python :: 3.12
Classifier: Topic :: Software Development :: Code Generators
Classifier: Topic :: Software Development :: Quality Assurance
Classifier: Topic :: Software Development :: Testing
Classifier: Operating System :: OS Independent
Requires-Python: >=3.8.1
License-File: LICENSE
Requires-Dist: antlr4-python3-runtime>=4.13.0
Requires-Dist: click>=8.0.0
Requires-Dist: pydantic>=2.0.0
Requires-Dist: rich>=13.0.0
Provides-Extra: dev
Requires-Dist: pytest>=7.0.0; extra == "dev"
Requires-Dist: pytest-cov>=4.0.0; extra == "dev"
Requires-Dist: black>=23.0.0; extra == "dev"
Requires-Dist: isort>=5.0.0; extra == "dev"
Requires-Dist: mypy>=1.0.0; extra == "dev"
Requires-Dist: flake8>=6.0.0; extra == "dev"
Dynamic: license-file
